qleaf/__init__.py
qleaf/proc.py
qleaf/comp/__init__.py
qleaf/comp/mplchart.py
qleaf/comp/advanced/__init__.py
qleaf/comp/advanced/dbtable.py
qleaf/comp/advanced/listviewSearch.py
qleaf/comp/basic/__init__.py
qleaf/comp/basic/form.py
qleaf/comp/basic/image.py
qleaf/comp/basic/lineEdit.py
qleaf/comp/basic/listview.py
qleaf/comp/basic/pushButton.py
qleaf/comp/basic/slider.py
qleaf/comp/basic/table.py
qleaf/comp/basic/text.py
qleaf/comp/basic/textEdit.py
qleaf/comp/basic/treeview.py
qleaf/comp/chart/__init__.py
qleaf/comp/chart/imShow.py
qleaf/comp/chart/lineGraph.py
qleaf/comp/chart/lineGraphEditor.py
qleaf/comp/chart/scatter.py
qleaf/comp/filesystem/__init__.py
qleaf/comp/filesystem/filelist.py
qleaf/comp/filesystem/path.py
qleaf/core/__init__.py
qleaf/core/abstract_comp.py
qleaf/core/image.py
qleaf/core/prop.py
qleaf/core/main_window/__init__.py
qleaf/core/main_window/gui.py
qleaf/core/main_window/state.py
qleaf/style/__init__.py
qleaf/style/Qutat/Qutat.qss
qleaf/style/Qutat/__init__.py
qleaf/style/Qutat/bt_main.qss
qleaf/style/Qutat/bt_standard.qss
qleaf/style/Qutat/label_standard.qss
qleaf/style/Qutat/le_standard.qss
qleaf/style/Qutat/list_standard.qss
qleaf/style/Qutat/table_standard.qss
qleaf-0.0.19.dist-info/licenses/LICENSE
qleaf-0.0.19.dist-info/METADATA
qleaf-0.0.19.dist-info/WHEEL
qleaf-0.0.19.dist-info/top_level.txt
qleaf-0.0.19.dist-info/RECORD
